.DS_Store
.gitignore
MANIFEST.in
README.md
setup.py
test.py
.git/FETCH_HEAD
.git/HEAD
.git/config
.git/description
.git/index
.git/packed-refs
.git/hooks/applypatch-msg.sample
.git/hooks/commit-msg.sample
.git/hooks/fsmonitor-watchman.sample
.git/hooks/post-update.sample
.git/hooks/pre-applypatch.sample
.git/hooks/pre-commit.sample
.git/hooks/pre-merge-commit.sample
.git/hooks/pre-push.sample
.git/hooks/pre-rebase.sample
.git/hooks/pre-receive.sample
.git/hooks/prepare-commit-msg.sample
.git/hooks/push-to-checkout.sample
.git/hooks/update.sample
.git/info/exclude
.git/logs/HEAD
.git/logs/refs/heads/main
.git/logs/refs/heads/master
.git/logs/refs/remotes/origin/main
.git/objects/05/b9de528dedb450119fe0ca954f3f287dfda7d6
.git/objects/0d/1b84309cd37e6d919a1f6893a5f714c150c2db
.git/objects/10/e4d40d5ae38e72e46c53ce7e7277d00c76a6b4
.git/objects/17/179535aaeaaf8b6524b143b63f98bcdbb348c8
.git/objects/1b/8512ff250e622b4b701c6795ff7781963e0b21
.git/objects/45/ee27da9da7646e9bf2d8d3485dcc3e6e9a557f
.git/objects/4b/d4674f5533ce101b12a0058cec133d9a70da19
.git/objects/50/08ddfcf53c02e82d7eee2e57c38e5672ef89f6
.git/objects/50/f1fcebc7cf38806de0b9fb7ec230c4fed5344a
.git/objects/58/630cca95b36f4b31eadac9abc07250fc4a506d
.git/objects/5f/9b664022517c6df0be23d6b9d282eb8935a9d7
.git/objects/61/ba3c72dbea0a6cece128f284e73a25b382972d
.git/objects/64/1a2a047c9949dd9d0abf53758a2d5680fdf326
.git/objects/65/122a2e7cbf89d075a3e55add8120755c5b440d
.git/objects/6d/b1a5e73f4cdd59f092cc56cd7395d825a0a3c0
.git/objects/6e/7dad02afd9279527463c8c6bbab4efe02d85a3
.git/objects/77/40d310f816ef3f16ebb54d39459d3e70676009
.git/objects/83/5193a18ee05ccd717eb9c8289969fdfc07bbe7
.git/objects/8b/137891791fe96927ad78e64b0aad7bded08bdc
.git/objects/8d/266abc4a72ad738d4eff5a45ae8be488cbfaec
.git/objects/a0/c016d6f41f7f3912a6e5736c8c6fa74db5263b
.git/objects/a5/448bde806f1c261c09997e091a096bd02496a8
.git/objects/ae/527a926d594f3a8231e98f0cc3ec795e98e174
.git/objects/b6/e47617de110dea7ca47e087ff1347cc2646eda
board_to_fen_proba.egg-info/PKG-INFO
board_to_fen_proba.egg-info/SOURCES.txt
board_to_fen_proba.egg-info/dependency_links.txt
board_to_fen_proba.egg-info/requires.txt
board_to_fen_proba.egg-info/top_level.txt